Metadata-Version: 2.1
Name: bitnesslib
Version: 0.2.0
Summary: Given a binary, determine its bitness
Home-page: https://github.com/ramikg/bitnesslib
License: UNKNOWN
Platform: UNKNOWN
Classifier: Programming Language :: Python :: 2
Classifier: Programming Language :: Python :: 3
